Workbook

Sheet 说明
A1: Workflow System 功能测试表
A2: 版本：v0.1.0（main） 编写日期：2026-10-12
A4: 怎么用
A5: 1. 在"测试用例"页从上往下测，P0 先测（必须通过才能上线），P1 次之，P2 有空再测。
A6: 2. 每条按"操作步骤"做，对照"预期结果"，在"测试结果"列下拉选：通过 / 不通过 / 阻塞 / 跳过。
A7: 3. 不通过时在"问题/备注"写清楚实际看到了什么（最好附截图文件名）。
A8: 4. "汇总"页会自动统计进度和通过率。
A10: "老系统要求"和"对照"两列
A11: 老系统要求：摘自 new-system-doc.md 第一部分，§ 是章节号。这是最低标准，新系统必须做到。
A12: 同等：与老系统一致。 增强：做到老系统的要求，并且更多。 新增：老系统没有。
A13: 差异：之前已决定有意改变做法（例如客户字段只存一份、删除改为回收站），测试时确认新做法业务上能接受。
A14: 待确认：代码里没看到老系统的这条规则，或行为可能不同。这几条请重点测，结果告诉我，再决定是否补。
... A24: 5. 数据迁移用 D:\Projects\Workflow System\csv sample 里的两个导出文件。

Sheet 汇总
A1: 模块 | B1: 用例数 | C1: P0 | D1: 已测 | E1: 通过 | F1: 不通过 | G1: 阻塞 | H1: 跳过 | I1: 未测 | J1: 通过率（已测）
A2: 登录与权限 | B2: =COUNTIF(测试用例!$B$2:$B$153,$A2) | C2: =COUNTIFS(测试用例!$B$2:$B$153,$A2,测试用例!$D$2:$D$153,"P0") | D2: =E2+F2+G2+H2 | E2: =COUNTIFS(测试用例!$B$2:$B$153,$A2,测试用例!$J$2:$J$153,"通过") | F2: =COUNTIFS(测试用例!$B$2:$B$153,$A2,测试用例!$J$2:$J$153,"不通过") | G2: =COUNTIFS(测试用例!$B$2:$B$153,$A2,测试用例!$J$2:$J$153,"阻塞") | H2: =COUNTIFS(测试用例!$B$2:$B$153,$A2,测试用例!$J$2:$J$153,"跳过") | I2: =B2-D2 | J2: =IF(D2-H2=0,"-",E2/(D2-H2))
A3: Home 与导航 | B3: =COUNTIF(测试用例!$B$2:$B$153,$A3) | C3: =COUNTIFS(测试用例!$B$2:$B$153,$A3,测试用例!$D$2:$D$153,"P0") | D3: =E3+F3+G3+H3 | E3: =COUNTIFS(测试用例!$B$2:$B$153,$A3,测试用例!$J$2:$J$153,"通过") | F3: =COUNTIFS(测试用例!$B$2:$B$153,$A3,测试用例!$J$2:$J$153,"不通过") | G3: =COUNTIFS(测试用例!$B$2:$B$153,$A3,测试用例!$J$2:$J$153,"阻塞") | H3: =COUNTIFS(测试用例!$B$2:$B$153,$A3,测试用例!$J$2:$J$153,"跳过") | I3: =B3-D3 | J3: =IF(D3-H3=0,"-",E3/(D3-H3))
A4: 客户 Clients | B4: =COUNTIF(测试用例!$B$2:$B$153,$A4) | C4: =COUNTIFS(测试用例!$B$2:$B$153,$A4,测试用例!$D$2:$D$153,"P0") | D4: =E4+F4+G4+H4 | E4: =COUNTIFS(测试用例!$B$2:$B$153,$A4,测试用例!$J$2:$J$153,"通过") | F4: =COUNTIFS(测试用例!$B$2:$B$153,$A4,测试用例!$J$2:$J$153,"不通过") | G4: =COUNTIFS(测试用例!$B$2:$B$153,$A4,测试用例!$J$2:$J$153,"阻塞") | H4: =COUNTIFS(测试用例!$B$2:$B$153,$A4,测试用例!$J$2:$J$153,"跳过") | I4: =B4-D4 | J4: =IF(D4-H4=0,"-",E4/(D4-H4))
A5: Accounting 看板 | B5: =COUNTIF(测试用例!$B$2:$B$153,$A5) | C5: =COUNTIFS(测试用例!$B$2:$B$153,$A5,测试用例!$D$2:$D$153,"P0") | D5: =E5+F5+G5+H5 | E5: =COUNTIFS(测试用例!$B$2:$B$153,$A5,测试用例!$J$2:$J$153,"通过") | F5: =COUNTIFS(测试用例!$B$2:$B$153,$A5,测试用例!$J$2:$J$153,"不通过") | G5: =COUNTIFS(测试用例!$B$2:$B$153,$A5,测试用例!$J$2:$J$153,"阻塞") | H5: =COUNTIFS(测试用例!$B$2:$B$153,$A5,测试用例!$J$2:$J$153,"跳过") | I5: =B5-D5 | J5: =IF(D5-H5=0,"-",E5/(D5-H5))
A6: Grants 看板 | B6: =COUNTIF(测试用例!$B$2:$B$153,$A6) | C6: =COUNTIFS(测试用例!$B$2:$B$153,$A6,测试用例!$D$2:$D$153,"P0") | D6: =E6+F6+G6+H6 | E6: =COUNTIFS(测试用例!$B$2:$B$153,$A6,测试用例!$J$2:$J$153,"通过") | F6: =COUNTIFS(测试用例!$B$2:$B$153,$A6,测试用例!$J$2:$J$153,"不通过") | G6: =COUNTIFS(测试用例!$B$2:$B$153,$A6,测试用例!$J$2:$J$153,"阻塞") | H6: =COUNTIFS(测试用例!$B$2:$B$153,$A6,测试用例!$J$2:$J$153,"跳过") | I6: =B6-D6 | J6: =IF(D6-H6=0,"-",E6/(D6-H6))
A7: 看板表格（两条线通用） | B7: =COUNTIF(测试用例!$B$2:$B$153,$A7) | C7: =COUNTIFS(测试用例!$B$2:$B$153,$A7,测试用例!$D$2:$D$153,"P0") | D7: =E7+F7+G7+H7 | E7: =COUNTIFS(测试用例!$B$2:$B$153,$A7,测试用例!$J$2:$J$153,"通过") | F7: =COUNTIFS(测试用例!$B$2:$B$153,$A7,测试用例!$J$2:$J$153,"不通过") | G7: =COUNTIFS(测试用例!$B$2:$B$153,$A7,测试用例!$J$2:$J$153,"阻塞") | H7: =COUNTIFS(测试用例!$B$2:$B$153,$A7,测试用例!$J$2:$J$153,"跳过") | I7: =B7-D7 | J7: =IF(D7-H7=0,"-",E7/(D7-H7))
A8: 新建项目 | B8: =COUNTIF(测试用例!$B$2:$B$153,$A8) | C8: =COUNTIFS(测试用例!$B$2:$B$153,$A8,测试用例!$D$2:$D$153,"P0") | D8: =E8+F8+G8+H8 | E8: =COUNTIFS(测试用例!$B$2:$B$153,$A8,测试用例!$J$2:$J$153,"通过") | F8: =COUNTIFS(测试用例!$B$2:$B$153,$A8,测试用例!$J$2:$J$153,"不通过") | G8: =COUNTIFS(测试用例!$B$2:$B$153,$A8,测试用例!$J$2:$J$153,"阻塞") | H8: =COUNTIFS(测试用例!$B$2:$B$153,$A8,测试用例!$J$2:$J$153,"跳过") | I8: =B8-D8 | J8: =IF(D8-H8=0,"-",E8/(D8-H8))
A9: Roll over | B9: =COUNTIF(测试用例!$B$2:$B$153,$A9) | C9: =COUNTIFS(测试用例!$B$2:$B$153,$A9,测试用例!$D$2:$D$153,"P0") | D9: =E9+F9+G9+H9 | E9: =COUNTIFS(测试用例!$B$2:$B$153,$A9,测试用例!$J$2:$J$153,"通过") | F9: =COUNTIFS(测试用例!$B$2:$B$153,$A9,测试用例!$J$2:$J$153,"不通过") | G9: =COUNTIFS(测试用例!$B$2:$B$153,$A9,测试用例!$J$2:$J$153,"阻塞") | H9: =COUNTIFS(测试用例!$B$2:$B$153,$A9,测试用例!$J$2:$J$153,"跳过") | I9: =B9-D9 | J9: =IF(D9-H9=0,"-",E9/(D9-H9))
A10: 归档、恢复与删除 | B10: =COUNTIF(测试用例!$B$2:$B$153,$A10) | C10: =COUNTIFS(测试用例!$B$2:$B$153,$A10,测试用例!$D$2:$D$153,"P0") | D10: =E10+F10+G10+H10 | E10: =COUNTIFS(测试用例!$B$2:$B$153,$A10,测试用例!$J$2:$J$153,"通过") | F10: =COUNTIFS(测试用例!$B$2:$B$153,$A10,测试用例!$J$2:$J$153,"不通过") | G10: =COUNTIFS(测试用例!$B$2:$B$153,$A10,测试用例!$J$2:$J$153,"阻塞") | H10: =COUNTIFS(测试用例!$B$2:$B$153,$A10,测试用例!$J$2:$J$153,"跳过") | I10: =B10-D10 | J10: =IF(D10-H10=0,"-",E10/(D10-H10))
A11: 任务 | B11: =COUNTIF(测试用例!$B$2:$B$153,$A11) | C11: =COUNTIFS(测试用例!$B$2:$B$153,$A11,测试用例!$D$2:$D$153,"P0") | D11: =E11+F11+G11+H11 | E11: =COUNTIFS(测试用例!$B$2:$B$153,$A11,测试用例!$J$2:$J$153,"通过") | F11: =COUNTIFS(测试用例!$B$2:$B$153,$A11,测试用例!$J$2:$J$153,"不通过") | G11: =COUNTIFS(测试用例!$B$2:$B$153,$A11,测试用例!$J$2:$J$153,"阻塞") | H11: =COUNTIFS(测试用例!$B$2:$B$153,$A11,测试用例!$J$2:$J$153,"跳过") | I11: =B11-D11 | J11: =IF(D11-H11=0,"-",E11/(D11-H11))
A12: 看板设置与配置 | B12: =COUNTIF(测试用例!$B$2:$B$153,$A12) | C12: =COUNTIFS(测试用例!$B$2:$B$153,$A12,测试用例!$D$2:$D$153,"P0") | D12: =E12+F12+G12+H12 | E12: =COUNTIFS(测试用例!$B$2:$B$153,$A12,测试用例!$J$2:$J$153,"通过") | F12: =COUNTIFS(测试用例!$B$2:$B$153,$A12,测试用例!$J$2:$J$153,"不通过") | G12: =COUNTIFS(测试用例!$B$2:$B$153,$A12,测试用例!$J$2:$J$153,"阻塞") | H12: =COUNTIFS(测试用例!$B$2:$B$153,$A12,测试用例!$J$2:$J$153,"跳过") | I12: =B12-D12 | J12: =IF(D12-H12=0,"-",E12/(D12-H12))
A13: 自动化 | B13: =COUNTIF(测试用例!$B$2:$B$153,$A13) | C13: =COUNTIFS(测试用例!$B$2:$B$153,$A13,测试用例!$D$2:$D$153,"P0") | D13: =E13+F13+G13+H13 | E13: =COUNTIFS(测试用例!$B$2:$B$153,$A13,测试用例!$J$2:$J$153,"通过") | F13: =COUNTIFS(测试用例!$B$2:$B$153,$A13,测试用例!$J$2:$J$153,"不通过") | G13: =COUNTIFS(测试用例!$B$2:$B$153,$A13,测试用例!$J$2:$J$153,"阻塞") | H13: =COUNTIFS(测试用例!$B$2:$B$153,$A13,测试用例!$J$2:$J$153,"跳过") | I13: =B13-D13 | J13: =IF(D13-H13=0,"-",E13/(D13-H13))
... A18: 数据迁移 | B18: =COUNTIF(测试用例!$B$2:$B$153,$A18) | C18: =COUNTIFS(测试用例!$B$2:$B$153,$A18,测试用例!$D$2:$D$153,"P0") | D18: =E18+F18+G18+H18 | E18: =COUNTIFS(测试用例!$B$2:$B$153,$A18,测试用例!$J$2:$J$153,"通过") | F18: =COUNTIFS(测试用例!$B$2:$B$153,$A18,测试用例!$J$2:$J$153,"不通过") | G18: =COUNTIFS(测试用例!$B$2:$B$153,$A18,测试用例!$J$2:$J$153,"阻塞") | H18: =COUNTIFS(测试用例!$B$2:$B$153,$A18,测试用例!$J$2:$J$153,"跳过") | I18: =B18-D18 | J18: =IF(D18-H18=0,"-",E18/(D18-H18))
A19: 合计 | B19: =SUM(B2:B18) | C19: =SUM(C2:C18) | D19: =SUM(D2:D18) | E19: =SUM(E2:E18) | F19: =SUM(F2:F18) | G19: =SUM(G2:G18) | H19: =SUM(H2:H18) | I19: =SUM(I2:I18) | J19: =IF(D19-H19=0,"-",E19/(D19-H19))
A21: P0 未通过（不通过 + 阻塞） | B21: =COUNTIFS(测试用例!$D$2:$D$153,"P0",测试用例!$J$2:$J$153,"不通过")+COUNTIFS(测试用例!$D$2:$D$153,"P0",测试用例!$J$2:$J$153,"阻塞")
A22: 上线条件：P0 全部通过；"待确认"项都有结论

Sheet 测试用例
A1: 编号 | B1: 模块 | C1: 功能点 | D1: 优先级 | E1: 前置条件 | F1: 操作步骤 | G1: 预期结果 | H1: 老系统要求（最低标准） | I1: 对照 | J1: 测试结果 | K1: 测试日期 | L1: 测试人 | M1: 问题/备注
A2: 01-01 | B2: 登录与权限 | C2: 正常登录 | D2: P0 | E2: 已有管理员账号 | F2: 1. 打开系统地址（如 http://localhost:8080） 2. 输入邮箱和密码，点登录 | G2: 进入 Home 页，左下角显示自己的名字 | H2: §3 产品登录页登录 | I2: 同等
A3: 01-02 | B3: 登录与权限 | C3: 密码错误 | D3: P0 | E3: 无 | F3: 1. 输入正确邮箱、错误密码，点登录 | G3: 提示登录失败，停留在登录页 | H3: §3 产品登录页登录 | I3: 同等
A4: 01-03 | B4: 登录与权限 | C4: 连续失败锁定 | D4: P2 | E4: 一个测试账号 | F4: 1. 用同一账号连续输错密码 9 次 2. 再输入正确密码 | G4: 第 8 次之后账号被锁 15 分钟，正确密码也暂时无法登录 | H4: 老系统无此要求 | I4: 新增
A5: 01-04 | B5: 登录与权限 | C5: 退出登录 | D5: P0 | E5: 已登录 | F5: 1. 点左下角退出图标 2. 浏览器点后退，或直接访问 /home | G5: 回到登录页；后退或直接访问都要求重新登录 | H5: §3 退出 | I5: 同等
A6: 01-05 | B6: 登录与权限 | C6: 未登录访问受保护页面 | D6: P0 | E6: 未登录 | F6: 1. 直接在地址栏打开 /clients 或某个看板地址 | G6: 被送回登录页；登录后回到刚才想去的页面 | H6: §3 普通用户被送回 /smart | I6: 同等
A7: 01-06 | B7: 登录与权限 | C7: 刷新保持登录 | D7: P1 | E7: 已登录 | F7: 1. 在任意页面按 F5 刷新 2. 关闭标签页再打开系统 | G7: 仍然是登录状态，不需要重新输入密码 | H7: 隐含要求 | I7: 同等
A8: 01-07 | B8: 登录与权限 | C8: 忘记密码（管理员重置） | D8: P1 | E8: 管理员账号 + 一个普通用户 A | F8: 1. A 在另一个浏览器保持登录 2. 管理员进 Users，给 A 设新密码 3. A 刷新页面 4. A 用新密码登录 | G8: 第 3 步 A 被登出（旧会话失效）；新密码可登录，旧密码不行 | H8: §3 登录页有"忘记密码"自助流程 | I8: 差异
A9: 01-08 | B9: 登录与权限 | C9: 只开通一个产品线 | D9: P0 | E9: 用户 B：只给 Accounting 的 member 角色 | F9: 1. 用 B 登录 2. 看顶部产品线切换 3. 手动把地址里的 /w/accounting/ 改成 /w/grants/ | G9: B 只看到 Accounting；手动访问 Grants 看不到数据或被拒绝 | H9: §3 只有 Smart Accounting User 才能进会计线，Grants 同理 | I9: 同等
A10: 01-09 | B10: 登录与权限 | C10: 列按产品线隔离 | D10: P0 | E10: 无 | F10: 1. 打开 Accounting 任一看板，点 Columns 看可选列 2. 打开 Grants 任一看板，同样查看 | G10: Accounting 看不到 Grant Type、AP Submit Date 等 Grants 列；Grants 看不到 Lodgement Due、Monthly Status 等会计列 | H10: §3 看板上的列按模块过滤 | I10: 同等
A11: 01-10 | B11: 登录与权限 | C11: viewer 只读 | D11: P1 | E11: 用户 C：Accounting 的 viewer 角色 | F11: 1. 用 C 登录，打开会计看板 2. 双击单元格尝试修改 3. 找 New 按钮、勾选行 | G11: 能看不能改：单元格不可编辑，没有新建按钮，勾选后没有批量操作 | H11: 老系统按 Frappe 读写权限，没有专门的只读角色 | I11: 增强
A12: 01-11 | B12: 登录与权限 | C12: member 与 manager 的区别 | D12: P1 | E12: 用户 B（member） | F12: 1. 用 B 勾选一行，看批量栏有没有 Delete 2. 打开 Automations 看能否新建规则 3. 保存视图时看能否选 Shared | G12: member 不能删除项目、不能管理自动化、不能建共享视图；manager 可以 | H12: §13 管自动化、看板设置需要管理员类角色 | I12: 增强
A13: 01-12 | B13: 登录与权限 | C13: 管理页面只对管理员开放 | D13: P0 | E13: 用户 B（非管理员） | F13: 1. 用 B 登录看左侧导航 2. 直接访问 /users 和 /system | G13: 导航里没有 Users、System health；直接访问看不到数据或被拒绝 | H13: §13 管用户需要管理员 | I13: 同等
... A153: 17-07 | B153: 数据迁移 | C153: 回滚整批导入 | D153: P0 | E153: 已有一次导入 | F153: 1. Roll back this import | G153: 这次导入创建的项目全部撤掉，更新过的恢复原值 | H153: 同上 | I153: 新增
